ennvee_commons/__init__.py
ennvee_commons/captcha_utils.py
ennvee_commons/common_error_handler.py
ennvee_commons/email_utils.py
ennvee_commons/logging_framework.py
ennvee_commons/res_middleware_utils.py
ennvee_commons/sms_utils.py
ennvee_commons/utils.py
ennvee_commons-0.1.1.dist-info/METADATA
ennvee_commons-0.1.1.dist-info/WHEEL
ennvee_commons-0.1.1.dist-info/top_level.txt
ennvee_commons-0.1.1.dist-info/RECORD
