Metadata-Version: 2.1
Name: ennvee-commons
Version: 0.1.1
Summary: Common utilities for ennVee organization
Author: Paavan Boddeda
Classifier: Programming Language :: Python :: 3
Classifier: License :: OSI Approved :: MIT License
Classifier: Operating System :: OS Independent
Requires-Python: >=3.8
Requires-Dist: requests>=2.31.0
Requires-Dist: twilio>=8.0.0
Requires-Dist: loguru>=0.7.0
Requires-Dist: starlette==0.47.1
